{"0": "affirm", "1": "ai", "2": "bot_challenge", "3": "businessconsult", "4": "businessintelligence", "5": "connect", "6": "contact", "7": "deny", "8": "description", "9": "django", "10": "email", "11": "flutter", "12": "getstarted", "13": "golang", "14": "goodbye", "15": "hireresource", "16": "homepage", "17": "inquiry", "18": "inquiryform", "19": "location", "20": "mood_great", "21": "mood_unhappy", "22": "name", "23": "number", "24": "officehours", "25": "pwa", "26": "python", "27": "reactjs", "28": "rpa", "29": "start", "30": "team"}